plain/api/CHANGELOG.md
plain/api/README.md
plain/api/__init__.py
plain/api/admin.py
plain/api/cli.py
plain/api/config.py
plain/api/default_settings.py
plain/api/models.py
plain/api/schemas.py
plain/api/versioning.py
plain/api/views.py
plain/api/migrations/0001_initial.py
plain/api/migrations/__init__.py
plain/api/openapi/__init__.py
plain/api/openapi/decorators.py
plain/api/openapi/generator.py
plain/api/openapi/utils.py
plain_api-0.26.0.dist-info/METADATA
plain_api-0.26.0.dist-info/WHEEL
plain_api-0.26.0.dist-info/licenses/LICENSE
plain_api-0.26.0.dist-info/RECORD
