Metadata-Version: 2.4
Name: plain.api
Version: 0.26.0
Summary: Build APIs using class-based views.
Author-email: Dave Gaeddert <dave.gaeddert@dropseed.dev>
License-Expression: BSD-3-Clause
License-File: LICENSE
Requires-Python: >=3.13
Requires-Dist: plain<1.0.0
